winpcapy/__init__.py
winpcapy/winpcapy.py
winpcapy/winpcapy_types.py
winpcapy-1.0.0.dist-info/DESCRIPTION.rst
winpcapy-1.0.0.dist-info/LICENSE.txt
winpcapy-1.0.0.dist-info/METADATA
winpcapy-1.0.0.dist-info/RECORD
winpcapy-1.0.0.dist-info/WHEEL
winpcapy-1.0.0.dist-info/metadata.json
winpcapy-1.0.0.dist-info/top_level.txt
